NRInsightsApi/__init__.py
NRInsightsApi/get_data.py
NRInsightsApi/insert_data.py
NRInsightsApi-0.0.2.dist-info/LICENSE
NRInsightsApi-0.0.2.dist-info/METADATA
NRInsightsApi-0.0.2.dist-info/WHEEL
NRInsightsApi-0.0.2.dist-info/top_level.txt
NRInsightsApi-0.0.2.dist-info/RECORD
