Metadata-Version: 2.1
Name: NRInsightsApi
Version: 0.0.2
Summary: REST API for New Relic
Home-page: https://github.com/vikramnr/newrelic-insights-api
Author: Vikram
Author-email: vikram1912@protonmail.com
License: UNKNOWN
Project-URL: Bug Tracker, https://github.com/vikramnr/newrelic-insights-api/issues
Platform: UNKNOWN
Classifier: Programming Language :: Python :: 3
Classifier: License :: OSI Approved :: MIT License
Classifier: Operating System :: OS Independent
Requires-Python: >=3.6
